{
  "users": [
    {
      "email": "maxjmg@mail.ru",
      "nickname": "root",
      "password": "123456",
      "firstName": "Maxim",
      "lastName": "Grishin",
      "gender": "Мужчина",
      "dateOfBirth": "07.04.2002",
      "about": "Aliquyam eos ipsum takimata ipsum dolor eos aliquyam sea dolores, et lorem consetetur sed ipsum kasd ipsum rebum amet dolores. Ea no sed eos gubergren, sadipscing et dolor invidunt nonumy sit no et. Diam accusam labore lorem et stet, accusam aliquyam eirmod et stet rebum stet clita invidunt, accusam clita.",
      "isCar": "Нет",
      "phoneNumber": 89877557031,
      "photoUrl": "https://sun9-50.userapi.com/impg/eDQ0-bfxtFgcHUTU8K230-4ZVomj9FGdM5CjHQ/F5zxhmD2OSM.jpg?size=900x900&quality=96&sign=5dfdaf9614ba07c9cc8f8b22e66e83ed&type=album",
      "id": 1
    },
    {
      "email": "1234124124@asfasg",
      "nickname": "masgasg",
      "password": "12345688",
      "id": 2
    }
  ],
  "rides": [
    {
      "name": "Нижний Новгород → Москва",
      "date": "31.12.2022",
      "description": "Без собак",
      "price": 1100,
      "author": "Кирилл",
      "contacts": 816921898878,
      "id": 1
    },
    {
      "name": "Ардатов → Санкт-Петербург",
      "date": "06.01.2023",
      "description": "Без кошек",
      "price": 900,
      "author": "Роман",
      "contacts": 864626157933,
      "id": 2
    },
    {
      "name": "Ардатов → Нижний Новгород",
      "date": "21.12.2022",
      "description": "",
      "price": 850,
      "author": "Иван",
      "contacts": 80462822133,
      "id": 3
    },
    {
      "name": "Тольятти → Самара",
      "date": "22.12.2023",
      "description": "",
      "price": 200,
      "author": "Илья",
      "contacts": 832804651987,
      "id": 4
    },
    {
      "name": "Екатеринбург → Челябинск",
      "date": "26.12.2022",
      "description": "",
      "price": 560,
      "author": "Анастасия",
      "contacts": 8347857223,
      "id": 5
    },
    {
      "name": "Барнаул → Новосибирск",
      "date": "20.02.2023",
      "description": "Во время поездки, курить нельзя",
      "price": 680,
      "author": "Эмир",
      "contacts": 81579112402,
      "id": 6
    },
    {
      "name": "Казань → Набережные Челны",
      "date": "13.01.2023",
      "description": "",
      "price": 620,
      "author": "Арина",
      "contacts": 85818938388,
      "id": 7
    },
    {
      "name": "Челябинск → Екатеринбург",
      "date": "29.12.2022",
      "description": "",
      "price": 560,
      "author": "Елисей",
      "contacts": 8649724882,
      "id": 8
    },
    {
      "name": "Кинешма → Северодвинск",
      "date": "28.02.2023",
      "description": "Оплата наличными",
      "price": 1800,
      "author": "Олег",
      "contacts": 8739822371,
      "id": 9
    },
    {
      "name": "Рязань → Москва",
      "date": "26.12.2022",
      "description": "",
      "price": 1210,
      "author": "Елизавета",
      "contacts": 83948856910,
      "id": 10
    },
    {
      "name": "test -> test",
      "date": "2022-12-07",
      "description": "adgasgasgasg",
      "price": "1233",
      "author": "asasg",
      "contacts": 1234567890,
      "id": 11
    }
  ]
}